cortado/__init__.py
cortado/data.py
cortado/evaluate.py
cortado/hill_climbing.py
cortado/marker_genes.py
cortado/utils.py
sc_cortado-0.1.22.dist-info/LICENSE
sc_cortado-0.1.22.dist-info/METADATA
sc_cortado-0.1.22.dist-info/WHEEL
sc_cortado-0.1.22.dist-info/top_level.txt
sc_cortado-0.1.22.dist-info/RECORD
